PythonPaystackv2/__init__.py
PythonPaystackv2/payment.py
PythonPaystackv2/status.py
PythonPaystackv2/subscription.py
pypstk/__init__.py
pypstk/payment.py
pypstk/status.py
pypstk/subscription.py
pypstk-0.1.0.dist-info/LIcence
pypstk-0.1.0.dist-info/METADATA
pypstk-0.1.0.dist-info/WHEEL
pypstk-0.1.0.dist-info/top_level.txt
pypstk-0.1.0.dist-info/RECORD
