Metadata-Version: 2.1
Name: pypstk
Version: 0.1.0
Home-page: https://github.com/emekadefirst/Paystack-Python-2-SDK
Author: Victor Chibuogwu Chukwuemeka aka Emekadefirst
Author-email: emekadefirst@gmail.com
Classifier: Programming Language :: Python :: 3
Classifier: License :: OSI Approved :: MIT License
Classifier: Operating System :: OS Independent
License-File: LIcence
Requires-Dist: requests >=2.26.0
